sep_mw4.cpython-39-x86_64-linux-gnu.so
sep_mw4-1.2.2.dist-info/WHEEL
sep_mw4-1.2.2.dist-info/AUTHORS.md
sep_mw4-1.2.2.dist-info/RECORD
sep_mw4-1.2.2.dist-info/top_level.txt
sep_mw4-1.2.2.dist-info/METADATA
