Metadata-Version: 2.1
Name: sep_mw4
Version: 1.2.2
Summary: Astronomical source extraction and photometry library
Home-page: https://github.com/mworion/sep_mw4
Author: Michael Wuertenberger
Author-email: michael@wuertenberger.org
License: LGPLv3+
Classifier: Development Status :: 5 - Production/Stable
Classifier: Programming Language :: Python :: 3
Classifier: License :: OSI Approved :: GNU Lesser General Public License v3 or later (LGPLv3+)
Classifier: Topic :: Scientific/Engineering :: Astronomy
Classifier: Intended Audience :: Science/Research
Requires-Python: >=3.5
License-File: AUTHORS.md
Requires-Dist: numpy
